sphinx_theme_h123/.gitignore
sphinx_theme_h123/__init__.py
sphinx_theme_h123/base.html
sphinx_theme_h123/genindex.html
sphinx_theme_h123/page.html
sphinx_theme_h123/search.html
sphinx_theme_h123/theme.conf
sphinx_theme_h123/partials/brand.html
sphinx_theme_h123/partials/footer.html
sphinx_theme_h123/partials/icons.html
sphinx_theme_h123/partials/mobile-header.html
sphinx_theme_h123/partials/related-pages.html
sphinx_theme_h123/partials/search.html
sphinx_theme_h123/static/.gitignore
sphinx_theme_h123/static/styles/theme.css
sphinx_theme_h123-0.0.3.dist-info/entry_points.txt
sphinx_theme_h123-0.0.3.dist-info/LICENSE
sphinx_theme_h123-0.0.3.dist-info/WHEEL
sphinx_theme_h123-0.0.3.dist-info/METADATA
sphinx_theme_h123-0.0.3.dist-info/RECORD
