Metadata-Version: 2.1
Name: sphinx-theme-h123
Version: 0.0.3
Summary: a simple, plain, solid sphinx theme 
Requires-Python: >=3.8
Classifier: Development Status :: 4 - Beta
Classifier: Framework :: Sphinx :: Theme
Classifier: Programming Language :: Python
Classifier: Programming Language :: Python :: 3
Classifier: License :: OSI Approved :: BSD License
Classifier: Topic :: Documentation
Classifier: Topic :: Software Development :: Documentation
Requires-Dist: sphinx >= 4.2
Requires-Dist: beautifulsoup4
